{"elements":[{"type":"source","instance_id":895806,"src_id":"mnist_values","param_values":{"train":{"val":true,"type":"bool"}}},{"type":"transform","instance_id":447043,"transform_id":"image_to_tensor","input":895806,"param_values":{}},{"type":"source","instance_id":28523,"src_id":"mnist_labels","param_values":{"train":{"val":true,"type":"bool"}}},{"type":"transform","instance_id":556872,"transform_id":"normalize","input":447043,"param_values":{"mean":{"val":0.1307,"type":"float"},"std_dev":{"val":0.3081,"type":"float"}}}],"value_output":556872,"label_output":28523}